{"parts":[{"id":1,"name":"Brakes","price":15.0,"stock":10,"min":1,"max":20,"machineId":111},{"id":2,"name":"Wheel","price":11.0,"stock":16,"min":1,"max":30,"machineId":222},{"id":3,"name":"Seat","price":10.0,"stock":10,"min":3,"max":22,"companyName":"Expert Seats"},{"id":4,"name":"Rim","price":56.99,"stock":15,"min":1,"max":20,"companyName":"Remmy's"}],"products":[{"id":1,"name":"Bicycle","price":299.99,"stock":5,"min":1,"max":5,"associatedParts":[1,2,2,3]},{"id":2,"name":"Tricycle","price":99.99,"stock":3,"min":1,"max":10,"associatedParts":[2,2,2,3]}]}